python_liquid_api/__init__.py
python_liquid_api/parameter_dict.py
python_liquid_api/private_api.py
python_liquid_api/public_api.py
python_liquid_api/test_note.py
python_liquid_api/utils.py
python_liquid_api_tths-0.4.0.dist-info/LICENSE
python_liquid_api_tths-0.4.0.dist-info/METADATA
python_liquid_api_tths-0.4.0.dist-info/WHEEL
python_liquid_api_tths-0.4.0.dist-info/top_level.txt
python_liquid_api_tths-0.4.0.dist-info/RECORD
