Metadata-Version: 2.1
Name: python-liquid-api-tths
Version: 0.4.0
Summary: Use Liquid API with Python
Home-page: https://github.com/kitataku/python_liquid_api_tths
Author: kitataku
Author-email: 
Maintainer: kitataku
Maintainer-email: 
License: MIT License
Platform: UNKNOWN
Requires-Python: >=3.6
License-File: LICENSE
Requires-Dist: PyJWT (>=2.1.0)
Requires-Dist: pandas (>=1.3.4)
Requires-Dist: numpy (>=1.20.3)
Requires-Dist: requests (>=2.27.1)
